streamlit_tz/__init__.py
streamlit_tz/frontend/index.html
streamlit_tz/frontend/main.js
streamlit_tz/frontend/streamlit-component-lib.js
streamlit_tz-0.1.1.dist-info/LICENSE
streamlit_tz-0.1.1.dist-info/METADATA
streamlit_tz-0.1.1.dist-info/WHEEL
streamlit_tz-0.1.1.dist-info/top_level.txt
streamlit_tz-0.1.1.dist-info/RECORD
