Metadata-Version: 2.1
Name: streamlit-tz
Version: 0.1.1
Summary: Streamlit component that returns the user browser IANA timezone
Home-page: https://github.com/parente/streamlit-tz
Author: Peter Parente
Author-email: parente@gmail.com
Requires-Python: >=3.7
License-File: LICENSE
Requires-Dist: streamlit >=1.2
Requires-Dist: jinja2
